texttactoe/__init__.py
texttactoe/__main__.py
texttactoe/app.py
texttactoe/player.py
texttactoe/player_panel.py
texttactoe/tttboard.py
texttactoe-0.1.0.dist-info/entry_points.txt
texttactoe-0.1.0.dist-info/LICENSE
texttactoe-0.1.0.dist-info/WHEEL
texttactoe-0.1.0.dist-info/METADATA
texttactoe-0.1.0.dist-info/RECORD
