Metadata-Version: 2.1
Name: texttactoe
Version: 0.1.0
Summary: A TUI to play tictactoe.
Home-page: https://github.com/JoseAndresMedina/TextTacToe
License: MIT
Keywords: tictactoe,game,textual
Author: Jose Medina
Author-email: jose.amedina96@gmail.com
Requires-Python: >=3.8,<4.0
Classifier: License :: OSI Approved :: MIT License
Classifier: Programming Language :: Python :: 3
Classifier: Programming Language :: Python :: 3.10
Classifier: Programming Language :: Python :: 3.8
Classifier: Programming Language :: Python :: 3.9
Requires-Dist: textual (>=0.1.18,<0.2.0)
Project-URL: Repository, https://github.com/JoseAndresMedina/TextTacToe
